DSDLab/LAB-4/q3/q3.v
module q3(w, y, z);
   input [3:0]w;
   output reg [1:0]y;
   output reg z;
   
   always @*
   begin
   z=1;
   casex(w)
     4'b1XXX: y=3;
     4'b01XX: y=2;
     4'b001X: y=1;
     4'b0001: y=0;
     default:
     	     begin
     	     	z=0;
     	     	y=2'b00;
     	     end
    endcase
    end
endmodule

DSDLab/LAB-4/q3/q3_tb.v
`timescale 1ns/1ns
`include "q3.v" 

module q3_tb();
reg [3:0]w;
wire [1:0]y;
wire z;  
integer i;

q3 ex1(w,y,z);
initial 
begin
	$dumpfile("q3_tb.vcd");
	$dumpvars(0,q3_tb);
	for(i=0;i<15;i=i+1)
    begin
		w=i;
		#20;
    end
	$display("Test Complete");
end

endmodule

DSDLab/LAB-4/q3/q3_tb.vcd
$date
	Sat Dec 16 14:40:59 2023
$end
$version
	Icarus Verilog
$end
$timescale
	1ns
$end
$scope module q3_tb $end
$var wire 1 ! z $end
$var wire 2 " y [1:0] $end
$var reg 4 # w [3:0] $end
$var integer 32 $ i [31:0] $end
$scope module ex1 $end
$var wire 4 % w [3:0] $end
$var reg 2 & y [1:0] $end
$var reg 1 ! z $end
$upscope $end
$upscope $end
$enddefinitions $end
#0
$dumpvars
b0 &
b0 %
b0 $
b0 #
b0 "
0!
$end
#20
1!
b1 #
b1 %
b1 $
#40
b1 "
b1 &
b10 #
b10 %
b10 $
#60
b11 #
b11 %
b11 $
#80
b10 "
b10 &
b100 #
b100 %
b100 $
#100
b101 #
b101 %
b101 $
#120
b110 #
b110 %
b110 $
#140
b111 #
b111 %
b111 $
#160
b11 "
b11 &
b1000 #
b1000 %
b1000 $
#180
b1001 #
b1001 %
b1001 $
#200
b1010 #
b1010 %
b1010 $
#220
b1011 #
b1011 %
b1011 $
#240
b1100 #
b1100 %
b1100 $
#260
b1101 #
b1101 %
b1101 $
#280
b1110 #
b1110 %
b1110 $
#300
b1111 $
