DSDLab/LAB-3/q2/q2.v
module q2(S,W,f);
    input [2:0]S;
    input [7:0]W;
    output reg f;
    always @ (S|W)
    begin
        case (S)
        0:begin
            f=W[0];
        end
        1:begin
            f=W[1];
        end
        2:begin
            f=W[2];
        end
        3:begin
            f=W[3];
        end
        4:begin
            f=W[4];
        end
        5:begin
            f=W[5];
        end
        6:begin
            f=W[6];
        end
        7:begin
            f=W[7];
        end
        default : begin
            f=0;
        end
        endcase
    end
endmodule

DSDLab/LAB-3/q2/q2_tb.v
`timescale 1ns/1ns
`include "q2.v" 

module q2_tb();
reg [2:0]S;
reg [7:0]W;
wire f;
integer i;

q2 ex1(S,W,f);
initial 
begin

	$dumpfile("q2_tb.vcd");
	$dumpvars(0,q2_tb);
	S=0;
	W=7'b1110110;
	#20

	S=1;
	W=7'b0011100;
	#20

	S=2;
	W=7'b0111001;
	#20

	S=3;
	W=7'b0100010;
	#20

	S=4;
	W=7'b0001100;
	#20

	S=5;
	W=7'b0101110;
	#20

	S=6;
	W=7'b1010011;
	#20

	S=7;
	W=7'b1001100;
	#20
	$display("Test Complete");
end

endmodule

DSDLab/LAB-3/q2/q2_tb.vcd
$date
	Sat Dec 16 09:23:16 2023
$end
$version
	Icarus Verilog
$end
$timescale
	1ns
$end
$scope module q2_tb $end
$var wire 1 ! f $end
$var reg 3 " S [2:0] $end
$var reg 8 # W [7:0] $end
$scope module ex1 $end
$var wire 3 $ S [2:0] $end
$var wire 8 % W [7:0] $end
$var reg 1 ! f $end
$upscope $end
$upscope $end
$enddefinitions $end
#0
$dumpvars
b1110110 %
b0 $
b1110110 #
b0 "
0!
$end
#20
b11100 #
b11100 %
b1 "
b1 $
#40
b111001 #
b111001 %
b10 "
b10 $
#60
b100010 #
b100010 %
b11 "
b11 $
#80
b1100 #
b1100 %
b100 "
b100 $
#100
1!
b101110 #
b101110 %
b101 "
b101 $
#120
b1010011 #
b1010011 %
b110 "
b110 $
#140
0!
b1001100 #
b1001100 %
b111 "
b111 $
