DSDLab/LAB-1/q3/q3.v
module q3(a,b,c,d,f);
	input a,b,c,d;
	output f;
	
	assign f = (b|~c)&(~b|c|~d)&(~c|d)&(a|~b|~d);
endmodule

DSDLab/LAB-1/q3/q3_tb.v
`timescale 1ns/1ns
`include "q3.v" 

module q3_tb();
reg a,b,c,d;
wire f;
integer i;

q3 ex1(a,b,c,d,f);
initial 
begin

	$dumpfile("q3_tb.vcd");
	$dumpvars(0,q3_tb);
	for(i=0; i<16; i=i+1) begin
		{a,b,c,d} = i;
		#20;
	end
	$display("Test Complete");
end

endmodule

DSDLab/LAB-1/q3/q3_tb.vcd
$date
	Wed Dec 13 15:08:24 2023
$end
$version
	Icarus Verilog
$end
$timescale
	1ns
$end
$scope module q3_tb $end
$var wire 1 ! f $end
$var reg 1 " a $end
$var reg 1 # b $end
$var reg 1 $ c $end
$var reg 1 % d $end
$var integer 32 & i [31:0] $end
$scope module ex1 $end
$var wire 1 " a $end
$var wire 1 # b $end
$var wire 1 $ c $end
$var wire 1 % d $end
$var wire 1 ! f $end
$upscope $end
$upscope $end
$enddefinitions $end
#0
$dumpvars
b0 &
0%
0$
0#
0"
1!
$end
#20
1%
b1 &
#40
0!
1$
0%
b10 &
#60
1%
b11 &
#80
1!
1#
0$
0%
b100 &
#100
0!
1%
b101 &
#120
1$
0%
b110 &
#140
1%
b111 &
#160
1!
1"
0#
0$
0%
b1000 &
#180
1%
b1001 &
#200
0!
1$
0%
b1010 &
#220
1%
b1011 &
#240
1!
1#
0$
0%
b1100 &
#260
0!
1%
b1101 &
#280
1$
0%
b1110 &
#300
1!
1%
b1111 &
#320
b10000 &
