DSDLab/LAB-4/q4/q4.v
module q4(w, y, z);
    input [15:0]w;
    output reg [3:0]y;
    output reg z;
    integer k;
    
    always @*
    begin
        z=0;
        y = 4'bxxxx;
        for (k=0;k<=15;k++) begin
            if (w[k] == 1) begin
                y = k;
                z = 1;
            end
        end
    end
endmodule

DSDLab/LAB-4/q4/q4_tb.v
`timescale 1ns/1ns
`include "q4.v" 

module q4_tb();
reg [15:0]w;
wire [3:0]y;
wire z;  
integer i;

q4 ex1(w,y,z);
initial 
begin
	$dumpfile("q4_tb.vcd");
	$dumpvars(0,q4_tb);
	for(i=0;i<16;i=i+1)
    begin
		w=i;
		#20;
    end
	$display("Test Complete");
end

endmodule

DSDLab/LAB-4/q4/q4_tb.vcd
$date
	Sat Dec 16 15:01:07 2023
$end
$version
	Icarus Verilog
$end
$timescale
	1ns
$end
$scope module q4_tb $end
$var wire 1 ! z $end
$var wire 4 " y [3:0] $end
$var reg 16 # w [15:0] $end
$var integer 32 $ i [31:0] $end
$scope module ex1 $end
$var wire 16 % w [15:0] $end
$var reg 4 & y [3:0] $end
$var reg 1 ! z $end
$var integer 32 ' k [31:0] $end
$upscope $end
$upscope $end
$enddefinitions $end
#0
$dumpvars
b10000 '
bx &
b0 %
b0 $
b0 #
bx "
0!
$end
#20
1!
b0 "
b0 &
b10000 '
b1 #
b1 %
b1 $
#40
b10000 '
b1 "
b1 &
1!
b10 #
b10 %
b10 $
#60
b10000 '
b1 "
b1 &
1!
b11 #
b11 %
b11 $
#80
b10000 '
b10 "
b10 &
1!
b100 #
b100 %
b100 $
#100
b10000 '
b10 "
b10 &
1!
b101 #
b101 %
b101 $
#120
b10000 '
b10 "
b10 &
1!
b110 #
b110 %
b110 $
#140
b10000 '
b10 "
b10 &
1!
b111 #
b111 %
b111 $
#160
b10000 '
b11 "
b11 &
1!
b1000 #
b1000 %
b1000 $
#180
b10000 '
b11 "
b11 &
1!
b1001 #
b1001 %
b1001 $
#200
b10000 '
b11 "
b11 &
1!
b1010 #
b1010 %
b1010 $
#220
b10000 '
b11 "
b11 &
1!
b1011 #
b1011 %
b1011 $
#240
b10000 '
b11 "
b11 &
1!
b1100 #
b1100 %
b1100 $
#260
b10000 '
b11 "
b11 &
1!
b1101 #
b1101 %
b1101 $
#280
b10000 '
b11 "
b11 &
1!
b1110 #
b1110 %
b1110 $
#300
b10000 '
b11 "
b11 &
1!
b1111 #
b1111 %
b1111 $
#320
b10000 $
