DSDLab/LAB-4/q2/q2.v
module q2(w,e,y);
    input [3:0] w;
    input e;
    output [0:15] y;
    wire [0:3]temp;
    ttf s0 (w[3:2], e, temp[0:3]);
    ttf s1 (w[1:0], temp[0], y[0:3]);
    ttf s2 (w[1:0], temp[1], y[4:7]);
    ttf s3 (w[1:0], temp[2], y[8:11]);
    ttf s4 (w[1:0], temp[3], y[12:15]);
endmodule

module ttf(w,e,y);
    input [1:0] w;
    input e;
    output reg [0:3] y;

    always @(e, w)
    begin 
    y = 4'b0000;
        if (w == 2'b00 && e == 1)
        y[0] = 1;
        else if (w == 2'b01 && e == 1)
        y[1] = 1;
        else if (w == 2'b10 && e == 1)
        y[2] = 1;
        else if (w == 2'b11 && e == 1)
        y[3] = 1;
    end
endmodule

DSDLab/LAB-4/q2/q2_tb.v
`timescale 1ns/1ns
`include "q2.v" 

module q2_tb();
reg [3:0]w;
wire [0:15]y;
reg e;
integer i;

q2 ex1(w,e,y);
initial 
begin

	$dumpfile("q2_tb.vcd");
	$dumpvars(0,q2_tb);
	for(i=0; i<8; i=i+1) begin
		w = i;
		e = 1;
		#20;
	end
	e = 0; w = 4'b1111; #20;
	$display("Test Complete");
end

endmodule

DSDLab/LAB-4/q2/q2_tb.vcd
$date
	Sat Dec 16 14:35:27 2023
$end
$version
	Icarus Verilog
$end
$timescale
	1ns
$end
$scope module q2_tb $end
$var wire 16 ! y [0:15] $end
$var reg 1 " e $end
$var reg 4 # w [3:0] $end
$var integer 32 $ i [31:0] $end
$scope module ex1 $end
$var wire 1 " e $end
$var wire 4 % w [3:0] $end
$var wire 16 & y [0:15] $end
$var wire 4 ' temp [0:3] $end
$scope module s0 $end
$var wire 1 " e $end
$var wire 2 ( w [1:0] $end
$var reg 4 ) y [0:3] $end
$upscope $end
$scope module s1 $end
$var wire 1 * e $end
$var wire 2 + w [1:0] $end
$var reg 4 , y [0:3] $end
$upscope $end
$scope module s2 $end
$var wire 1 - e $end
$var wire 2 . w [1:0] $end
$var reg 4 / y [0:3] $end
$upscope $end
$scope module s3 $end
$var wire 1 0 e $end
$var wire 2 1 w [1:0] $end
$var reg 4 2 y [0:3] $end
$upscope $end
$scope module s4 $end
$var wire 1 3 e $end
$var wire 2 4 w [1:0] $end
$var reg 4 5 y [0:3] $end
$upscope $end
$upscope $end
$upscope $end
$enddefinitions $end
#0
$dumpvars
b0 5
b0 4
03
b0 2
b0 1
00
b0 /
b0 .
0-
b1000 ,
b0 +
1*
b1000 )
b0 (
b1000 '
b1000000000000000 &
b0 %
b0 $
b0 #
1"
b1000000000000000 !
$end
#20
b100000000000000 !
b100000000000000 &
b100 ,
b1 +
b1 .
b1 1
b1 4
b1 #
b1 %
b1 $
#40
b10000000000000 !
b10000000000000 &
b10 ,
b10 +
b10 .
b10 1
b10 4
b10 #
b10 %
b10 $
#60
b1000000000000 !
b1000000000000 &
b1 ,
b11 +
b11 .
b11 1
b11 4
b11 #
b11 %
b11 $
#80
b1000 /
1-
0*
b100 '
b100 )
b100000000000 !
b100000000000 &
b0 ,
b1 (
b0 +
b0 .
b0 1
b0 4
b100 #
b100 %
b100 $
#100
b10000000000 !
b10000000000 &
b100 /
b1 +
b1 .
b1 1
b1 4
b101 #
b101 %
b101 $
#120
b1000000000 !
b1000000000 &
b10 /
b10 +
b10 .
b10 1
b10 4
b110 #
b110 %
b110 $
#140
b100000000 !
b100000000 &
b1 /
b11 +
b11 .
b11 1
b11 4
b111 #
b111 %
b111 $
#160
b0 !
b0 &
b0 /
0-
b11 (
b0 '
b0 )
b1111 #
b1111 %
0"
b1000 $
