DSDLab/LAB-3/q1/q1.v
module q1(S,W,f);
    input [1:0]S;
    input [3:0]W;
    output reg f;
    always @ (S|W)
    begin
    if (S==0)
        f = W[0];
    else if (S==1)
        f = W[1];
    else if (S==2)
        f = W[2];
    else
        f = W[3];
    end
endmodule

DSDLab/LAB-3/q1/q1_tb.v
`timescale 1ns/1ns
`include "q1.v" 

module q1_tb();
reg [1:0]S;
reg [3:0]W;
wire f;
integer i;

q1 ex1(S,W,f);
initial 
begin

	$dumpfile("q1_tb.vcd");
	$dumpvars(0,q1_tb);
	S=0;
	W=4'b1110;
	#20

	S=1;
	W=4'b0011;
	#20

	S=2;
	W=4'b0111;
	#20

	S=3;
	W=4'b0000;
	#20

	S=0;
	W=4'b0001;
	#20

	S=1;
	W=4'b0101;
	#20

	S=2;
	W=4'b1010;
	#20

	S=3;
	W=4'b 1001;
	#20
	$display("Test Complete");
end

endmodule

DSDLab/LAB-3/q1/q1_tb.vcd
$date
	Sat Dec 16 09:31:29 2023
$end
$version
	Icarus Verilog
$end
$timescale
	1ns
$end
$scope module q1_tb $end
$var wire 1 ! f $end
$var reg 2 " S [1:0] $end
$var reg 4 # W [3:0] $end
$scope module ex1 $end
$var wire 2 $ S [1:0] $end
$var wire 4 % W [3:0] $end
$var reg 1 ! f $end
$upscope $end
$upscope $end
$enddefinitions $end
#0
$dumpvars
b1110 %
b0 $
b1110 #
b0 "
0!
$end
#20
1!
b11 #
b11 %
b1 "
b1 $
#40
b111 #
b111 %
b10 "
b10 $
#60
0!
b0 #
b0 %
b11 "
b11 $
#80
1!
b1 #
b1 %
b0 "
b0 $
#100
0!
b101 #
b101 %
b1 "
b1 $
#120
b1010 #
b1010 %
b10 "
b10 $
#140
1!
b1001 #
b1001 %
b11 "
b11 $
