DSDLab/LAB-2/q2/q2.v
module q2(a,b,cin,sum,cout);
    input a,b,cin;
    output sum, cout;
    assign sum = a^b^cin;
    assign cout = (a&b)|(b&cin)|(cin&a);
endmodule

DSDLab/LAB-2/q2/q2_tb.v
`timescale 1ns/1ns
`include "q2.v" 

module q2_tb();
reg a,b,cin;
wire sum,cout;
integer i;

q2 ex1(a,b,cin,sum,cout);
initial 
begin

	$dumpfile("q2_tb.vcd");
	$dumpvars(0,q2_tb);
	for(i=0; i<12; i=i+1) begin
		{a,b,cin} = i;
		#20;
	end
	$display("Test Complete");
end

endmodule

DSDLab/LAB-2/q2/q2_tb.vcd
$date
	Wed Dec 13 15:41:26 2023
$end
$version
	Icarus Verilog
$end
$timescale
	1ns
$end
$scope module q2_tb $end
$var wire 1 ! sum $end
$var wire 1 " cout $end
$var reg 1 # a $end
$var reg 1 $ b $end
$var reg 1 % cin $end
$var integer 32 & i [31:0] $end
$scope module ex1 $end
$var wire 1 # a $end
$var wire 1 $ b $end
$var wire 1 % cin $end
$var wire 1 " cout $end
$var wire 1 ! sum $end
$upscope $end
$upscope $end
$enddefinitions $end
#0
$dumpvars
b0 &
0%
0$
0#
0"
0!
$end
#20
1!
1%
b1 &
#40
1!
1$
0%
b10 &
#60
1"
0!
1%
b11 &
#80
0"
1!
1#
0$
0%
b100 &
#100
1"
0!
1%
b101 &
#120
1"
0!
1$
0%
b110 &
#140
1!
1%
b111 &
#160
0"
0!
0#
0$
0%
b1000 &
#180
1!
1%
b1001 &
#200
1!
1$
0%
b1010 &
#220
1"
0!
1%
b1011 &
#240
b1100 &
