DSDLab/LAB-1/q1/q1.v
module q1(a,b,c,d,f);
	input a,b,c,d;
	output f;
	not(g, c);
	assign f = (c)|(a&g&d);
endmodule

DSDLab/LAB-2/q1/q1_tb.v
`timescale 1ns/1ns
`include "q1.v" 

module q1_tb();
reg a,b,c,d;
wire f;
integer i;

q1 ex1(a,b,c,d,f);
initial 
begin

	$dumpfile("q1_tb.vcd");
	$dumpvars(0,q1_tb);
	for(i=0; i<16; i=i+1) begin
		{a,b,c,d} = i;
		#20;
	end
	$display("Test Complete");
end

endmodule

DSDLab/LAB-1/q1/q1_tb.vcd
$date
	Wed Dec 13 14:45:59 2023
$end
$version
	Icarus Verilog
$end
$timescale
	1ns
$end
$scope module q1_tb $end
$var wire 1 ! f $end
$var reg 1 " a $end
$var reg 1 # b $end
$var reg 1 $ c $end
$var reg 1 % d $end
$var integer 32 & i [31:0] $end
$scope module ex1 $end
$var wire 1 " a $end
$var wire 1 # b $end
$var wire 1 $ c $end
$var wire 1 % d $end
$var wire 1 ! f $end
$var wire 1 ' g $end
$upscope $end
$upscope $end
$enddefinitions $end
#0
$dumpvars
1'
b0 &
0%
0$
0#
0"
0!
$end
#20
1%
b1 &
#40
0'
1!
1$
0%
b10 &
#60
1%
b11 &
#80
1'
0!
1#
0$
0%
b100 &
#100
1%
b101 &
#120
0'
1!
1$
0%
b110 &
#140
1%
b111 &
#160
1'
0!
1"
0#
0$
0%
b1000 &
#180
1!
1%
b1001 &
#200
0'
1$
0%
b1010 &
#220
1%
b1011 &
#240
1'
0!
1#
0$
0%
b1100 &
#260
1!
1%
b1101 &
#280
0'
1$
0%
b1110 &
#300
1%
b1111 &
#320
b10000 &
