DSDLab/LAB-5/q2/q2.v
module q2(g,b);
    input [3:0]g;
    output [3:0]b;
    wire [0:7]m3,m2,m1,m0;
    assign m3=8'b00001111;
    assign m2=8'b00111100;
    assign m1=8'b01101001;
    assign m0={g[0],~g[0],~g[0],g[0],~g[0],g[0],g[0],~g[0]};
    mux8to1 st0(g[3:1],m3,b[3]);
    mux8to1 st1(g[3:1],m2,b[2]);
    mux8to1 st2(g[3:1],m1,b[1]);
    mux8to1 st3(g[3:1],m0,b[0]);
endmodule

module mux8to1(s,w,f);
    input [0:7]w;
    input [2:0]s;
    output reg f;
    always @(w or s)
    case(s)
        3'b000:f=w[0];
        3'b001:f=w[1];
        3'b010:f=w[2];
        3'b011:f=w[3];
        3'b100:f=w[4];
        3'b101:f=w[5];
        3'b110:f=w[6];
        3'b111:f=w[7];
    endcase
endmodule

DSDLab/LAB-5/q2/q2_tb.v
`timescale 1ns/1ns
`include "q2.v" 

module q2_tb();
reg [3:0]g;
wire [3:0]b;
integer i;

q2 ex1(g,b);
initial 
begin

	$dumpfile("q2_tb.vcd");
	$dumpvars(0,q2_tb);
	for(i=0; i<15; i=i+1) begin
		g = i;
		#20;
	end
	$display("Test Complete");
end

endmodule

DSDLab/LAB-5/q2/q2_tb.vcd
$date
	Sat Dec 16 10:16:05 2023
$end
$version
	Icarus Verilog
$end
$timescale
	1ns
$end
$scope module q2_tb $end
$var wire 4 ! b [3:0] $end
$var reg 4 " g [3:0] $end
$var integer 32 # i [31:0] $end
$scope module ex1 $end
$var wire 4 $ g [3:0] $end
$var wire 8 % m1 [0:7] $end
$var wire 8 & m2 [0:7] $end
$var wire 8 ' m3 [0:7] $end
$var wire 8 ( m0 [0:7] $end
$var wire 4 ) b [3:0] $end
$scope module st0 $end
$var wire 3 * s [2:0] $end
$var wire 8 + w [0:7] $end
$var reg 1 , f $end
$upscope $end
$scope module st1 $end
$var wire 3 - s [2:0] $end
$var wire 8 . w [0:7] $end
$var reg 1 / f $end
$upscope $end
$scope module st2 $end
$var wire 3 0 s [2:0] $end
$var wire 8 1 w [0:7] $end
$var reg 1 2 f $end
$upscope $end
$scope module st3 $end
$var wire 3 3 s [2:0] $end
$var wire 8 4 w [0:7] $end
$var reg 1 5 f $end
$upscope $end
$upscope $end
$upscope $end
$enddefinitions $end
#0
$dumpvars
05
b1101001 4
b0 3
02
b1101001 1
b0 0
0/
b111100 .
b0 -
0,
b1111 +
b0 *
b0 )
b1101001 (
b1111 '
b111100 &
b1101001 %
b0 $
b0 #
b0 "
b0 !
$end
#20
b1 !
b1 )
15
b10010110 (
b10010110 4
b1 "
b1 $
b1 #
#40
12
b11 !
b11 )
15
b1101001 (
b1101001 4
b1 *
b1 -
b1 0
b1 3
b10 "
b10 $
b10 #
#60
b10 !
b10 )
05
b10010110 (
b10010110 4
b11 "
b11 $
b11 #
#80
15
b111 !
b111 )
1/
b1101001 (
b1101001 4
b10 *
b10 -
b10 0
b10 3
b100 "
b100 $
b100 #
#100
b110 !
b110 )
05
b10010110 (
b10010110 4
b101 "
b101 $
b101 #
#120
b100 !
b100 )
02
b1101001 (
b1101001 4
b11 *
b11 -
b11 0
b11 3
b110 "
b110 $
b110 #
#140
b101 !
b101 )
15
b10010110 (
b10010110 4
b111 "
b111 $
b111 #
#160
1,
12
b1111 !
b1111 )
15
b1101001 (
b1101001 4
b100 *
b100 -
b100 0
b100 3
b1000 "
b1000 $
b1000 #
#180
b1110 !
b1110 )
05
b10010110 (
b10010110 4
b1001 "
b1001 $
b1001 #
#200
b1100 !
b1100 )
02
b1101001 (
b1101001 4
b101 *
b101 -
b101 0
b101 3
b1010 "
b1010 $
b1010 #
#220
b1101 !
b1101 )
15
b10010110 (
b10010110 4
b1011 "
b1011 $
b1011 #
#240
0/
b1000 !
b1000 )
05
b1101001 (
b1101001 4
b110 *
b110 -
b110 0
b110 3
b1100 "
b1100 $
b1100 #
#260
b1001 !
b1001 )
15
b10010110 (
b10010110 4
b1101 "
b1101 $
b1101 #
#280
12
b1011 !
b1011 )
15
b1101001 (
b1101001 4
b111 *
b111 -
b111 0
b111 3
b1110 "
b1110 $
b1110 #
#300
b1111 #
